{"tconst": "tt15232542", "titleType": "tvSeries", "primaryTitle": "American Sports Story", "originalTitle": null, "isAdult": "0", "startYear": "2024", "endYear": null, "episodes": [["tt23135230", 1, 1, 7.4, 263, "If It's to Be", "2024"], ["tt28296813", 1, 2, 7.4, 233, "Consequences, with Extreme Prejudice", "2024"], ["tt28296814", 1, 3, 7.4, 210, "Pray the Gay Away", "2024"], ["tt28296815", 1, 4, 7.6, 186, "Birthday Money", "2024"], ["tt30841336", 1, 5, 7.6, 179, "The Man", "2024"], ["tt30841339", 1, 6, 7.6, 173, "Herald Street", "2024"], ["tt30841340", 1, 7, 7.6, 155, "Dirty Pain", "2024"], ["tt30841346", 1, 8, 8.0, 169, "Odin", "2024"], ["tt31546262", 1, 9, 7.7, 148, "What's Left Behind", "2024"], ["tt31494977", 1, 10, 7.4, 152, "Who Killed Aaron Hernandez?", "2024"]]}