{"tconst": "tt0162796", "titleType": "tvSeries", "primaryTitle": "Bump in the Night", "originalTitle": "Bump in the Night", "isAdult": "0", "startYear": "1994", "endYear": "1995", "episodes": [{"tconst": "tt0911186", "parentTconst": "tt0162796", "seasonNumber": 1, "episodeNumber": 1, "averageRating": 7.7, "numVotes": 16, "primaryTitle": "Made in Japan/Dr. Coddle, M.D.", "originalTitle": null, "startYear": "1994", "endYear": "\\N"}, {"tconst": "tt1322488", "parentTconst": "tt0162796", "seasonNumber": 1, "episodeNumber": 2, "averageRating": 8.6, "numVotes": 12, "primaryTitle": "Gum Crazy/Baby Snail", "originalTitle": null, "startYear": "1994", "endYear": "\\N"}, {"tconst": "tt1322489", "parentTconst": "tt0162796", "seasonNumber": 1, "episodeNumber": 3, "averageRating": 7.4, "numVotes": 9, "primaryTitle": "Hide and Go Freak/Better Homes & Garbage", "originalTitle": null, "startYear": "1994", "endYear": "\\N"}, {"tconst": "tt1322495", "parentTconst": "tt0162796", "seasonNumber": 1, "episodeNumber": 4, "averageRating": 7.8, "numVotes": 10, "primaryTitle": "Not of This Boy's Room/To Sleep Perchance to Burp", "originalTitle": null, "startYear": "1994", "endYear": "\\N"}, {"tconst": "tt1322487", "parentTconst": "tt0162796", "seasonNumber": 1, "episodeNumber": 5, "averageRating": 7.2, "numVotes": 9, "primaryTitle": "Danger: Unexploded Squishington/Loss of Face", "originalTitle": null, "startYear": "1994", "endYear": "\\N"}, {"tconst": "tt1322498", "parentTconst": "tt0162796", "seasonNumber": 1, "episodeNumber": 6, "averageRating": 8.0, "numVotes": 10, "primaryTitle": "Sock It to Me/Comforting the Uncomfortable", "originalTitle": null, "startYear": "1994", "endYear": "\\N"}, {"tconst": "tt1322486", "parentTconst": "tt0162796", "seasonNumber": 1, "episodeNumber": 7, "averageRating": 8.5, "numVotes": 11, "primaryTitle": "Baby Jail/Night of the Living Bread", "originalTitle": null, "startYear": "1994", "endYear": "\\N"}, {"tconst": "tt1322496", "parentTconst": "tt0162796", "seasonNumber": 1, "episodeNumber": 8, "averageRating": 7.7, "numVotes": 10, "primaryTitle": "Party Poopers", "originalTitle": null, "startYear": "1994", "endYear": "\\N"}, {"tconst": "tt1322483", "parentTconst": "tt0162796", "seasonNumber": 1, "episodeNumber": 9, "averageRating": 7.8, "numVotes": 8, "primaryTitle": "A Sneeze in Time/Hocus Dopus", "originalTitle": null, "startYear": "1994", "endYear": "\\N"}, {"tconst": "tt1322484", "parentTconst": "tt0162796", "seasonNumber": 1, "episodeNumber": 10, "averageRating": 8.0, "numVotes": 9, "primaryTitle": "Adventures in Microbia/Not a Peep!", "originalTitle": null, "startYear": "1994", "endYear": "\\N"}, {"tconst": "tt1322497", "parentTconst": "tt0162796", "seasonNumber": 1, "episodeNumber": 11, "averageRating": 8.2, "numVotes": 9, "primaryTitle": "Penny for Your Thoughts/Farewell 2 Arms", "originalTitle": null, "startYear": "1994", "endYear": "\\N"}, {"tconst": "tt1322490", "parentTconst": "tt0162796", "seasonNumber": 1, "episodeNumber": 12, "averageRating": null, "numVotes": null, "primaryTitle": "I Dream of Silverfish/Story Problems", "originalTitle": null, "startYear": "1994", "endYear": "\\N"}, {"tconst": "tt1322499", "parentTconst": "tt0162796", "seasonNumber": 1, "episodeNumber": 13, "averageRating": 7.5, "numVotes": 12, "primaryTitle": "All You Need Is Glove/The Bowl of the Squishy Prince", "originalTitle": null, "startYear": "1994", "endYear": "\\N"}, {"tconst": "tt1322493", "parentTconst": "tt0162796", "seasonNumber": 2, "episodeNumber": 1, "averageRating": null, "numVotes": null, "primaryTitle": "Long Long Day/Destructo's Flipside", "originalTitle": null, "startYear": "1995", "endYear": "\\N"}, {"tconst": "tt0533643", "parentTconst": "tt0162796", "seasonNumber": 2, "episodeNumber": 2, "averageRating": null, "numVotes": null, "primaryTitle": "Love Stinks/Love's Labor Bumped", "originalTitle": null, "startYear": "1995", "endYear": "\\N"}, {"tconst": "tt1322492", "parentTconst": "tt0162796", "seasonNumber": 2, "episodeNumber": 3, "averageRating": 5.6, "numVotes": 9, "primaryTitle": "It Sang from Beyond the Stars/Journey to the Center of the Lungfish", "originalTitle": null, "startYear": "1995", "endYear": "\\N"}, {"tconst": "tt1322485", "parentTconst": "tt0162796", "seasonNumber": 2, "episodeNumber": 4, "averageRating": null, "numVotes": null, "primaryTitle": "Auntie Matta/Bumpy the Untrappable", "originalTitle": null, "startYear": "1995", "endYear": "\\N"}, {"tconst": "tt1323100", "parentTconst": "tt0162796", "seasonNumber": 2, "episodeNumber": 5, "averageRating": null, "numVotes": null, "primaryTitle": "It Came from the Closet", "originalTitle": null, "startYear": "1995", "endYear": "\\N"}, {"tconst": "tt1323099", "parentTconst": "tt0162796", "seasonNumber": 2, "episodeNumber": 6, "averageRating": null, "numVotes": null, "primaryTitle": "Comfort Schmumfort", "originalTitle": null, "startYear": "1995", "endYear": "\\N"}, {"tconst": "tt1323098", "parentTconst": "tt0162796", "seasonNumber": 2, "episodeNumber": 7, "averageRating": null, "numVotes": null, "primaryTitle": "Bump and Roll", "originalTitle": null, "startYear": "1995", "endYear": "\\N"}, {"tconst": "tt1322491", "parentTconst": "tt0162796", "seasonNumber": 2, "episodeNumber": 8, "averageRating": null, "numVotes": null, "primaryTitle": "I Got Needs/Beauty and the Bump", "originalTitle": null, "startYear": "1995", "endYear": "\\N"}, {"tconst": "tt1323102", "parentTconst": "tt0162796", "seasonNumber": 2, "episodeNumber": 9, "averageRating": null, "numVotes": null, "primaryTitle": "When the Music Starts", "originalTitle": null, "startYear": "1995", "endYear": "\\N"}, {"tconst": "tt1322494", "parentTconst": "tt0162796", "seasonNumber": 2, "episodeNumber": 10, "averageRating": null, "numVotes": null, "primaryTitle": "Neat and Clean/Nothing But the Tooth", "originalTitle": null, "startYear": "1995", "endYear": "\\N"}, {"tconst": "tt1322500", "parentTconst": "tt0162796", "seasonNumber": 2, "episodeNumber": 11, "averageRating": 7.0, "numVotes": 9, "primaryTitle": "Water Way to Go/Cold Turkey", "originalTitle": null, "startYear": "1995", "endYear": "\\N"}, {"tconst": "tt1237091", "parentTconst": "tt0162796", "seasonNumber": 2, "episodeNumber": 12, "averageRating": 7.0, "numVotes": 10, "primaryTitle": "Made in Japan II", "originalTitle": null, "startYear": "1995", "endYear": "\\N"}, {"tconst": "tt1323101", "parentTconst": "tt0162796", "seasonNumber": 2, "episodeNumber": 13, "averageRating": null, "numVotes": null, "primaryTitle": "Not a Leg to Stand On", "originalTitle": null, "startYear": "1995", "endYear": "\\N"}]}