{"tconst": "tt1898575", "titleType": "tvSeries", "primaryTitle": "Gigolos", "originalTitle": "Gigolos", "isAdult": "0", "startYear": "2011", "endYear": "2016", "episodes": [{"tconst": "tt1908789", "parentTconst": "tt1898575", "seasonNumber": 1, "episodeNumber": 1, "averageRating": 6.1, "numVotes": 30, "primaryTitle": "Date Night", "originalTitle": null, "startYear": "2011", "endYear": "\\N"}, {"tconst": "tt1908788", "parentTconst": "tt1898575", "seasonNumber": 1, "episodeNumber": 2, "averageRating": 5.6, "numVotes": 24, "primaryTitle": "All 4 One", "originalTitle": null, "startYear": "2011", "endYear": "\\N"}, {"tconst": "tt1908790", "parentTconst": "tt1898575", "seasonNumber": 1, "episodeNumber": 3, "averageRating": 6.0, "numVotes": 22, "primaryTitle": "Release the Kraken!", "originalTitle": null, "startYear": "2011", "endYear": "\\N"}, {"tconst": "tt1910007", "parentTconst": "tt1898575", "seasonNumber": 1, "episodeNumber": 4, "averageRating": 5.4, "numVotes": 23, "primaryTitle": "Three Gigolos and a Baby", "originalTitle": null, "startYear": "2011", "endYear": "\\N"}, {"tconst": "tt1910008", "parentTconst": "tt1898575", "seasonNumber": 1, "episodeNumber": 5, "averageRating": 6.1, "numVotes": 24, "primaryTitle": "Dance Dance Gigoloution", "originalTitle": null, "startYear": "2011", "endYear": "\\N"}, {"tconst": "tt1935459", "parentTconst": "tt1898575", "seasonNumber": 1, "episodeNumber": 6, "averageRating": 6.2, "numVotes": 24, "primaryTitle": "Birthday Sex", "originalTitle": null, "startYear": "2011", "endYear": "\\N"}, {"tconst": "tt1946904", "parentTconst": "tt1898575", "seasonNumber": 1, "episodeNumber": 7, "averageRating": 5.9, "numVotes": 22, "primaryTitle": "One Shot, One Opportunity", "originalTitle": null, "startYear": "2011", "endYear": "\\N"}, {"tconst": "tt1962712", "parentTconst": "tt1898575", "seasonNumber": 1, "episodeNumber": 8, "averageRating": 5.5, "numVotes": 18, "primaryTitle": "The Ties That Unbind", "originalTitle": null, "startYear": "2011", "endYear": "\\N"}, {"tconst": "tt8884266", "parentTconst": "tt1898575", "seasonNumber": 1, "episodeNumber": 9, "averageRating": 6.4, "numVotes": 9, "primaryTitle": "The Guys", "originalTitle": null, "startYear": "2011", "endYear": "\\N"}, {"tconst": "tt2148123", "parentTconst": "tt1898575", "seasonNumber": 2, "episodeNumber": 1, "averageRating": 6.2, "numVotes": 15, "primaryTitle": "Gigo-loan", "originalTitle": null, "startYear": "2011", "endYear": "\\N"}, {"tconst": "tt2216679", "parentTconst": "tt1898575", "seasonNumber": 2, "episodeNumber": 2, "averageRating": 5.8, "numVotes": 15, "primaryTitle": "Get Down on the Strip", "originalTitle": null, "startYear": "2011", "endYear": "\\N"}, {"tconst": "tt2216681", "parentTconst": "tt1898575", "seasonNumber": 2, "episodeNumber": 3, "averageRating": 6.2, "numVotes": 15, "primaryTitle": "The Boyfriend Experience", "originalTitle": null, "startYear": "2011", "endYear": "\\N"}, {"tconst": "tt2216683", "parentTconst": "tt1898575", "seasonNumber": 2, "episodeNumber": 4, "averageRating": 6.4, "numVotes": 17, "primaryTitle": "Really Smooth Operators", "originalTitle": null, "startYear": "2011", "endYear": "\\N"}, {"tconst": "tt2216685", "parentTconst": "tt1898575", "seasonNumber": 2, "episodeNumber": 5, "averageRating": 5.9, "numVotes": 16, "primaryTitle": "Poker? Heck, Yeah I'll Poker", "originalTitle": null, "startYear": "2011", "endYear": "\\N"}, {"tconst": "tt2216687", "parentTconst": "tt1898575", "seasonNumber": 2, "episodeNumber": 6, "averageRating": 7.1, "numVotes": 16, "primaryTitle": "An Ex Marks the Spot", "originalTitle": null, "startYear": "2011", "endYear": "\\N"}, {"tconst": "tt2216689", "parentTconst": "tt1898575", "seasonNumber": 2, "episodeNumber": 7, "averageRating": 6.5, "numVotes": 14, "primaryTitle": "Giggle-O's", "originalTitle": null, "startYear": "2011", "endYear": "\\N"}, {"tconst": "tt2216691", "parentTconst": "tt1898575", "seasonNumber": 2, "episodeNumber": 8, "averageRating": 6.3, "numVotes": 14, "primaryTitle": "Brotherly Love", "originalTitle": null, "startYear": "2011", "endYear": "\\N"}, {"tconst": "tt2823010", "parentTconst": "tt1898575", "seasonNumber": 3, "episodeNumber": 1, "averageRating": 6.0, "numVotes": 14, "primaryTitle": "The Steven Clown Affair", "originalTitle": null, "startYear": "2012", "endYear": "\\N"}, {"tconst": "tt2823048", "parentTconst": "tt1898575", "seasonNumber": 3, "episodeNumber": 2, "averageRating": 6.2, "numVotes": 15, "primaryTitle": "Searching for a Fire Power", "originalTitle": null, "startYear": "2012", "endYear": "\\N"}, {"tconst": "tt2823044", "parentTconst": "tt1898575", "seasonNumber": 3, "episodeNumber": 3, "averageRating": 6.2, "numVotes": 14, "primaryTitle": "Ride Her, Cowboy", "originalTitle": null, "startYear": "2012", "endYear": "\\N"}, {"tconst": "tt2823074", "parentTconst": "tt1898575", "seasonNumber": 3, "episodeNumber": 4, "averageRating": 7.1, "numVotes": 14, "primaryTitle": "Grin & Bear It", "originalTitle": null, "startYear": "2012", "endYear": "\\N"}, {"tconst": "tt2823042", "parentTconst": "tt1898575", "seasonNumber": 3, "episodeNumber": 5, "averageRating": 6.8, "numVotes": 14, "primaryTitle": "Courtesan Session", "originalTitle": null, "startYear": "2012", "endYear": "\\N"}, {"tconst": "tt2823060", "parentTconst": "tt1898575", "seasonNumber": 3, "episodeNumber": 6, "averageRating": 6.5, "numVotes": 14, "primaryTitle": "Spanks a Lot", "originalTitle": null, "startYear": "2012", "endYear": "\\N"}, {"tconst": "tt2823112", "parentTconst": "tt1898575", "seasonNumber": 3, "episodeNumber": 7, "averageRating": 7.0, "numVotes": 13, "primaryTitle": "Black Cock Down", "originalTitle": null, "startYear": "2012", "endYear": "\\N"}, {"tconst": "tt2823028", "parentTconst": "tt1898575", "seasonNumber": 3, "episodeNumber": 8, "averageRating": 6.2, "numVotes": 15, "primaryTitle": "A Decent Proposal", "originalTitle": null, "startYear": "2012", "endYear": "\\N"}, {"tconst": "tt2823046", "parentTconst": "tt1898575", "seasonNumber": 3, "episodeNumber": 9, "averageRating": 6.4, "numVotes": 14, "primaryTitle": "Lock, Stock & Two Swollen Testicles", "originalTitle": null, "startYear": "2012", "endYear": "\\N"}, {"tconst": "tt2823066", "parentTconst": "tt1898575", "seasonNumber": 3, "episodeNumber": 10, "averageRating": 6.2, "numVotes": 15, "primaryTitle": "The Porn Ultimatum", "originalTitle": null, "startYear": "2012", "endYear": "\\N"}, {"tconst": "tt2913946", "parentTconst": "tt1898575", "seasonNumber": 4, "episodeNumber": 1, "averageRating": 6.1, "numVotes": 16, "primaryTitle": "Thank the Lords", "originalTitle": null, "startYear": "2013", "endYear": "\\N"}, {"tconst": "tt2963494", "parentTconst": "tt1898575", "seasonNumber": 4, "episodeNumber": 2, "averageRating": 6.1, "numVotes": 14, "primaryTitle": "Bro Choice", "originalTitle": null, "startYear": "2013", "endYear": "\\N"}, {"tconst": "tt2963496", "parentTconst": "tt1898575", "seasonNumber": 4, "episodeNumber": 3, "averageRating": 6.9, "numVotes": 14, "primaryTitle": "The Spurt Locker", "originalTitle": null, "startYear": "2013", "endYear": "\\N"}, {"tconst": "tt2963500", "parentTconst": "tt1898575", "seasonNumber": 4, "episodeNumber": 4, "averageRating": 7.0, "numVotes": 13, "primaryTitle": "Make Mine a Double", "originalTitle": null, "startYear": "2013", "endYear": "\\N"}, {"tconst": "tt2963502", "parentTconst": "tt1898575", "seasonNumber": 4, "episodeNumber": 5, "averageRating": 7.0, "numVotes": 13, "primaryTitle": "Don't Judge a Gigolo by His Cover", "originalTitle": null, "startYear": "2013", "endYear": "\\N"}, {"tconst": "tt2963504", "parentTconst": "tt1898575", "seasonNumber": 4, "episodeNumber": 6, "averageRating": 7.1, "numVotes": 14, "primaryTitle": "Just for Licks", "originalTitle": null, "startYear": "2013", "endYear": "\\N"}, {"tconst": "tt3511248", "parentTconst": "tt1898575", "seasonNumber": 4, "episodeNumber": 7, "averageRating": 6.9, "numVotes": 12, "primaryTitle": "And the Winner Is", "originalTitle": null, "startYear": "2013", "endYear": "\\N"}, {"tconst": "tt3511258", "parentTconst": "tt1898575", "seasonNumber": 4, "episodeNumber": 8, "averageRating": 7.2, "numVotes": 11, "primaryTitle": "Smell of Success", "originalTitle": null, "startYear": "2013", "endYear": "\\N"}, {"tconst": "tt3518500", "parentTconst": "tt1898575", "seasonNumber": 4, "episodeNumber": 9, "averageRating": 7.2, "numVotes": 11, "primaryTitle": "Smile for the Camera", "originalTitle": null, "startYear": "2013", "endYear": "\\N"}, {"tconst": "tt3511380", "parentTconst": "tt1898575", "seasonNumber": 4, "episodeNumber": 10, "averageRating": 7.1, "numVotes": 11, "primaryTitle": "Reverend Brace", "originalTitle": null, "startYear": "2013", "endYear": "\\N"}, {"tconst": "tt3595752", "parentTconst": "tt1898575", "seasonNumber": 5, "episodeNumber": 1, "averageRating": 6.1, "numVotes": 12, "primaryTitle": "Creative Outlet", "originalTitle": null, "startYear": "2014", "endYear": "\\N"}, {"tconst": "tt3595768", "parentTconst": "tt1898575", "seasonNumber": 5, "episodeNumber": 2, "averageRating": 6.1, "numVotes": 12, "primaryTitle": "Centaur", "originalTitle": null, "startYear": "2014", "endYear": "\\N"}, {"tconst": "tt3595774", "parentTconst": "tt1898575", "seasonNumber": 5, "episodeNumber": 3, "averageRating": 5.9, "numVotes": 12, "primaryTitle": "Officer Nick Hawk", "originalTitle": null, "startYear": "2014", "endYear": "\\N"}, {"tconst": "tt3595784", "parentTconst": "tt1898575", "seasonNumber": 5, "episodeNumber": 4, "averageRating": 6.0, "numVotes": 12, "primaryTitle": "Rap Battle", "originalTitle": null, "startYear": "2014", "endYear": "\\N"}, {"tconst": "tt3595788", "parentTconst": "tt1898575", "seasonNumber": 5, "episodeNumber": 5, "averageRating": 5.3, "numVotes": 11, "primaryTitle": "RIP Zeus", "originalTitle": null, "startYear": "2014", "endYear": "\\N"}, {"tconst": "tt3595798", "parentTconst": "tt1898575", "seasonNumber": 5, "episodeNumber": 6, "averageRating": 5.9, "numVotes": 12, "primaryTitle": "Buff Bagwell", "originalTitle": null, "startYear": "2014", "endYear": "\\N"}, {"tconst": "tt3595800", "parentTconst": "tt1898575", "seasonNumber": 5, "episodeNumber": 7, "averageRating": 5.6, "numVotes": 11, "primaryTitle": "Pole a Palooza", "originalTitle": null, "startYear": "2014", "endYear": "\\N"}, {"tconst": "tt3595804", "parentTconst": "tt1898575", "seasonNumber": 5, "episodeNumber": 8, "averageRating": 5.7, "numVotes": 11, "primaryTitle": "Professor Brace", "originalTitle": null, "startYear": "2014", "endYear": "\\N"}, {"tconst": "tt3806864", "parentTconst": "tt1898575", "seasonNumber": 5, "episodeNumber": 9, "averageRating": 5.6, "numVotes": 12, "primaryTitle": "Top Gun", "originalTitle": null, "startYear": "2014", "endYear": "\\N"}, {"tconst": "tt3806876", "parentTconst": "tt1898575", "seasonNumber": 5, "episodeNumber": 10, "averageRating": 5.9, "numVotes": 11, "primaryTitle": "Vin Learns to Swim", "originalTitle": null, "startYear": "2014", "endYear": "\\N"}, {"tconst": "tt5589102", "parentTconst": "tt1898575", "seasonNumber": 6, "episodeNumber": 1, "averageRating": 6.3, "numVotes": 15, "primaryTitle": "I Popped Your Nervous Cherry", "originalTitle": null, "startYear": "2016", "endYear": "\\N"}, {"tconst": "tt5589110", "parentTconst": "tt1898575", "seasonNumber": 6, "episodeNumber": 2, "averageRating": 6.5, "numVotes": 14, "primaryTitle": "Double Date", "originalTitle": null, "startYear": "2016", "endYear": "\\N"}, {"tconst": "tt5673784", "parentTconst": "tt1898575", "seasonNumber": 6, "episodeNumber": 3, "averageRating": 6.8, "numVotes": 13, "primaryTitle": "Brace's Nephews", "originalTitle": null, "startYear": "2016", "endYear": "\\N"}, {"tconst": "tt5673790", "parentTconst": "tt1898575", "seasonNumber": 6, "episodeNumber": 4, "averageRating": 6.0, "numVotes": 11, "primaryTitle": "The Ringmaster", "originalTitle": null, "startYear": "2016", "endYear": "\\N"}, {"tconst": "tt5673796", "parentTconst": "tt1898575", "seasonNumber": 6, "episodeNumber": 5, "averageRating": 5.2, "numVotes": 11, "primaryTitle": "Monkey Business", "originalTitle": null, "startYear": "2016", "endYear": "\\N"}, {"tconst": "tt5673808", "parentTconst": "tt1898575", "seasonNumber": 6, "episodeNumber": 6, "averageRating": 4.8, "numVotes": 11, "primaryTitle": "A Little Country in You", "originalTitle": null, "startYear": "2016", "endYear": "\\N"}, {"tconst": "tt5673812", "parentTconst": "tt1898575", "seasonNumber": 6, "episodeNumber": 7, "averageRating": 5.0, "numVotes": 9, "primaryTitle": "Ultimate Warrior", "originalTitle": null, "startYear": "2016", "endYear": "\\N"}, {"tconst": "tt5711064", "parentTconst": "tt1898575", "seasonNumber": 6, "episodeNumber": 8, "averageRating": 4.7, "numVotes": 8, "primaryTitle": "Brace Tries Pulling Out", "originalTitle": null, "startYear": "2016", "endYear": "\\N"}]}